dinosar/__init__.py
dinosar/archive/__init__.py
dinosar/archive/asf/__init__.py
dinosar/archive/plot/__init__.py
dinosar/cli/__init__.py
dinosar/cli/get_inventory_asf.py
dinosar/cli/plot_inventory_asf.py
dinosar/cli/prep_topsApp_local.py
dinosar/isce/__init__.py
dinosar/isce/amplitude-cog.cpt
dinosar/isce/coherence-cog.cpt
dinosar/isce/topsApp-dinosar-template.yml
dinosar/isce/unwrapped-phase-cog.cpt
dinosar-0.1.4.dist-info/entry_points.txt
dinosar-0.1.4.dist-info/LICENSE
dinosar-0.1.4.dist-info/WHEEL
dinosar-0.1.4.dist-info/METADATA
dinosar-0.1.4.dist-info/RECORD
