Metadata-Version: 2.1
Name: dinosar
Version: 0.1.4
Summary: SAR processing on the Cloud
Home-page: https://github.com/scottyhq/dinosar
License: MIT
Keywords: SAR,Cloud,Batch,AWS
Author: Scott Henderson
Author-email: scotty@uw.edu
Requires-Python: >=3.6.1,<4.0.0
Classifier: License :: OSI Approved :: MIT License
Classifier: Programming Language :: Python :: 3
Classifier: Programming Language :: Python :: 3.7
Classifier: Programming Language :: Python :: 3.8
Provides-Extra: docs
Provides-Extra: vis
Requires-Dist: cartopy (>=0.18,<0.19); extra == "vis"
Requires-Dist: geopandas (>=0.8,<0.9)
Requires-Dist: lxml (>=4.4,<5.0)
Requires-Dist: matplotlib (>=3.1,<4.0)
Requires-Dist: pandas (>=1.0,<2.0)
Requires-Dist: pyyaml (>=5.2,<6.0)
Requires-Dist: requests (>=2.22,<3.0)
Requires-Dist: shapely (>=1.6,<2.0)
Requires-Dist: sphinx (>=2.3,<3.0); extra == "docs"
Requires-Dist: sphinx_rtd_theme (>=0.4,<0.5); extra == "docs"
Requires-Dist: sphinxcontrib-apidoc (>=0.3,<0.4); extra == "docs"
Project-URL: Repository, https://github.com/scottyhq/dinosar
